{"1":[{"w":"וַ/יַּגִּ֥דוּ","s":"H5046","m":"Hc/Vhw3mp","g":"and/ people told"},{"w":"לְ/דָוִ֖ד","s":"H1732","m":"HR/Npm","g":"to/ David"},{"w":"לֵ/אמֹ֑ר","s":"H0559","m":"HR/Vqcc","g":"<to>/ saying"},{"w":"הִנֵּ֤ה","s":"H2009","m":"HTj","l":"הִנֵּה","g":"there!"},{"w":"פְלִשְׁתִּים֙","s":"H6430","m":"HNgmpa","l":"פְּלִשְׁתִּי","g":"[the] Philistines"},{"w":"נִלְחָמִ֣ים","s":"H3898","m":"HVNrmpa","l":"לָחַם","g":"[are] fighting"},{"w":"בִּ/קְעִילָ֔ה","s":"H7084","m":"HR/Npl","g":"against/ Keilah"},{"w":"וְ/הֵ֖מָּה","s":"H1992","m":"HC/Pp3mp","g":"and/ they"},{"w":"שֹׁסִ֥ים","s":"H8154","m":"HVqrmpa","l":"שָׁסָה","g":"[are] plundering"},{"w":"אֶת\\־","s":"H0853","m":"HTo","l":"אֵת","g":"<obj.>"},{"w":"הַ/גֳּרָנֽוֹת\\׃","s":"H1637","m":"HTd/Ncfpa","g":"the/ threshing floors"}],"2":[{"w":"וַ/יִּשְׁאַ֨ל","s":"H7592","m":"Hc/Vqw3ms","g":"and/ he enquired"},{"w":"דָּוִ֤ד","s":"H1732","m":"HNpm","l":"דָּוִד","g":"David"},{"w":"בַּֽ/יהוָה֙","s":"H3068","m":"HR/Npt","g":"by/ Yahweh"},{"w":"לֵ/אמֹ֔ר","s":"H0559","m":"HR/Vqcc","g":"<to>/ saying"},{"w":"הַ/אֵלֵ֣ךְ","s":"H1980","m":"HTi/Vqi1cs","g":"¿/ will I go"},{"w":"וְ/הִכֵּ֔יתִי","s":"H5221","m":"Hc/Vhq1cs","g":"and/ will I strike?"},{"w":"בַּ/פְּלִשְׁתִּ֖ים","s":"H6430","m":"HRd/Ngmpa","g":"<in> the/ Philistines"},{"w":"הָ/אֵ֑לֶּה\\ \\ס","s":"H0428","m":"HTd/Tm","g":"<the>/ these"},{"w":"וַ/יֹּ֨אמֶר","s":"H0559","m":"Hc/Vqw3ms","g":"and/ he said"},{"w":"יְהוָ֜ה","s":"H3068","m":"HNpt","l":"יהוה","g":"Yahweh"},{"w":"אֶל\\־","s":"H0413","m":"HR","l":"אֶל","g":"to"},{"w":"דָּוִ֗ד","s":"H1732","m":"HNpm","l":"דָּוִד","g":"David"},{"w":"לֵ֚ךְ","s":"H1980","m":"HVqv2ms","l":"הָלַךְ","g":"go"},{"w":"וְ/הִכִּ֣יתָ","s":"H5221","m":"Hc/Vhq2ms","g":"and/ you will strike"},{"w":"בַ/פְּלִשְׁתִּ֔ים","s":"H6430","m":"HRd/Ngmpa","g":"<in> the/ Philistines"},{"w":"וְ/הוֹשַׁעְתָּ֖","s":"H3467","m":"Hc/Vhq2ms","g":"and/ you will deliver"},{"w":"אֶת\\־","s":"H0853","m":"HTo","l":"אֵת","g":"<obj.>"},{"w":"קְעִילָֽה\\׃","s":"H7084","m":"HNpl","l":"קְעִילָה","g":"Keilah"}],"3":[{"w":"וַ/יֹּ֨אמְר֜וּ","s":"H0559","m":"Hc/Vqw3mp","g":"and/ they said"},{"w":"אַנְשֵׁ֤י","s":"H0582","m":"HNcmpc","l":"אֱנוֹשׁ","g":"[the] men of"},{"w":"דָוִד֙","s":"H1732","m":"HNpm","l":"דָּוִד","g":"David"},{"w":"אֵלָ֔י/ו","s":"H0413","m":"HRd/Sp3ms","l":"אֶל","g":"to/ him"},{"w":"הִנֵּ֨ה","s":"H2009","m":"HTj","l":"הִנֵּה","g":"here!"},{"w":"אֲנַ֥חְנוּ","s":"H0587","m":"HPp1bp","l":"אֲנַ֫חְנוּ","g":"we"},{"w":"פֹ֛ה","s":"H6311","m":"HD","l":"פֹּה","g":"here"},{"w":"בִּֽ/יהוּדָ֖ה","s":"H3063","m":"HR/Npl","g":"in/ Judah"},{"w":"יְרֵאִ֑ים","s":"H3373","m":"HAampa","l":"יָרֵא","g":"[are] fearful"},{"w":"וְ/אַף֙","s":"H0637","m":"HC/Tj","g":"and/ indeed?"},{"w":"כִּֽי\\־","s":"H3588","m":"HTc","l":"כִּי","g":"if"},{"w":"נֵלֵ֣ךְ","s":"H1980","m":"HVqi1cp","l":"הָלַךְ","g":"we will go"},{"w":"קְעִלָ֔ה","s":"H7084","m":"HNpl","l":"קְעִילָה","g":"Keilah"},{"w":"אֶל\\־","s":"H0413","m":"HR","l":"אֶל","g":"against"},{"w":"מַֽעַרְכ֖וֹת","s":"H4634","m":"HNcfpc","l":"מַעֲרָכָה","g":"[the] battle lines of"},{"w":"פְּלִשְׁתִּֽים\\׃\\ \\ס","s":"H6430","m":"HNgmpa","l":"פְּלִשְׁתִּי","g":"[the] Philistines"}],"4":[{"w":"וַ/יּ֨וֹסֶף","s":"H3254","m":"Hc/Vhw3ms","g":"and/ he repeated"},{"w":"ע֤וֹד","s":"H5750","m":"HAcmsa","l":"עוֹד","g":"again"},{"w":"דָּוִד֙","s":"H1732","m":"HNpm","l":"דָּוִד","g":"David"},{"w":"לִ/שְׁאֹ֣ל","s":"H7592","m":"HR/Vqcc","g":"to/ enquire"},{"w":"בַּֽ/יהוָ֔ה\\ \\ס","s":"H3068","m":"HR/Npt","g":"by/ Yahweh"},{"w":"וַֽ/יַּעֲנֵ֖/הוּ","s":"H6030","m":"Hc/Vqw3ms/Sp3ms","g":"and/ he answered/ him"},{"w":"יְהוָ֑ה","s":"H3068","m":"HNpt","l":"יהוה","g":"Yahweh"},{"w":"וַ/יֹּ֗אמֶר","s":"H0559","m":"Hc/Vqw3ms","g":"and/ he said"},{"w":"ק֚וּם","s":"H6965","m":"HVqv2ms","l":"קוּם","g":"arise"},{"w":"רֵ֣ד","s":"H3381","m":"HVqv2ms","l":"יָרַד","g":"go down"},{"w":"קְעִילָ֔ה","s":"H7084","m":"HNpl","l":"קְעִילָה","g":"Keilah"},{"w":"כִּֽי\\־","s":"H3588","m":"HTc","l":"כִּי","g":"for"},{"w":"אֲנִ֥י","s":"H0589","m":"HPp1bs","l":"אֲנִי, אָֽנֹכִ֫י","g":"I"},{"w":"נֹתֵ֛ן","s":"H5414","m":"HVqrmsa","l":"נָתַן","g":"[am] about to give"},{"w":"אֶת\\־","s":"H0853","m":"HTo","l":"אֵת","g":"<obj.>"},{"w":"פְּלִשְׁתִּ֖ים","s":"H6430","m":"HNgmpa","l":"פְּלִשְׁתִּי","g":"[the] Philistines"},{"w":"בְּ/יָדֶֽ/ךָ\\׃","s":"H3027","m":"HR/Ncbsc/Sp2ms","g":"in/ hand/ your"}],"5":[{"w":"וַ/יֵּ֣לֶךְ","s":"H1980","m":"Hc/Vqw3ms","g":"and/ he went"},{"w":"דָּוִד֩","s":"H1732","m":"HNpm","l":"דָּוִד","g":"David"},{"w":"וַ/אֲנָשָׁ֨י/ו","s":"H0582","m":"HC/Ncmpc/Sp3ms","g":"and/ men/ his"},{"w":"קְעִילָ֜ה","s":"H7084","m":"HNpl","l":"קְעִילָה","g":"Keilah"},{"w":"וַ/יִּלָּ֣חֶם","s":"H3898","m":"Hc/VNw3ms","g":"and/ he fought"},{"w":"בַּ/פְּלִשְׁתִּ֗ים","s":"H6430","m":"HRd/Ngmpa","g":"against the/ Philistines"},{"w":"וַ/יִּנְהַג֙","s":"H5090","m":"Hc/Vqw3ms","g":"and/ he drove away"},{"w":"אֶת\\־","s":"H0853","m":"HTo","l":"אֵת","g":"<obj.>"},{"w":"מִקְנֵי/הֶ֔ם","s":"H4735","m":"HNcmsc/Sp3mp","l":"מִקְנֶה","g":"livestock/ their"},{"w":"וַ/יַּ֥ךְ","s":"H5221","m":"Hc/Vhw3ms","g":"and/ he defeated"},{"w":"בָּ/הֶ֖ם","s":"H9038","m":"HRd/Sp3mp","g":"<in> <the>/ them"},{"w":"מַכָּ֣ה","s":"H4347","m":"HNcfsa","l":"מַכָּה","g":"a defeat"},{"w":"גְדוֹלָ֑ה","s":"H1419","m":"HAafsa","l":"גַּל","g":"great"},{"w":"וַ/יֹּ֣שַׁע","s":"H3467","m":"Hc/Vhw3ms","g":"and/ he delivered"},{"w":"דָּוִ֔ד","s":"H1732","m":"HNpm","l":"דָּוִד","g":"David"},{"w":"אֵ֖ת","s":"H0853","m":"HTo","l":"אֵת","g":"<obj.>"},{"w":"יֹשְׁבֵ֥י","s":"H3427","m":"HVqrmpc","l":"יָשַׁב","g":"[the] inhabitants of"},{"w":"קְעִילָֽה\\׃\\ \\ס","s":"H7084","m":"HNpl","l":"קְעִילָה","g":"Keilah"}],"6":[{"w":"וַ/יְהִ֗י","s":"H1961","m":"Hc/Vqw3ms","g":"and/ it was"},{"w":"בִּ֠/בְרֹחַ","s":"H1272","m":"HR/Vqcc","g":"when/ fled"},{"w":"אֶבְיָתָ֧ר","s":"H0054","m":"HNpm","l":"אֶבְיָתָר","g":"Abiathar"},{"w":"בֶּן\\־","s":"H1121","m":"HNcmsc","l":"בֵּן","g":"[the] son of"},{"w":"אֲחִימֶ֛לֶךְ","s":"H0288","m":"HNpm","l":"אֲחִימֶ֫לֶךְ","g":"Ahimelech"},{"w":"אֶל\\־","s":"H0413","m":"HR","l":"אֶל","g":"to"},{"w":"דָּוִ֖ד","s":"H1732","m":"HNpm","l":"דָּוִד","g":"David"},{"w":"קְעִילָ֑ה","s":"H7084","m":"HNpl","l":"קְעִילָה","g":"Keilah"},{"w":"אֵפ֖וֹד","s":"H0646","m":"HNcmsa","l":"אֵפוֹד","g":"an ephod"},{"w":"יָרַ֥ד","s":"H3381","m":"HVqp3ms","l":"יָרַד","g":"it came down"},{"w":"בְּ/יָדֽ/וֹ\\׃","s":"H3027","m":"HR/Ncbsc/Sp3ms","g":"in/ hand/ his"}],"7":[{"w":"וַ/יֻּגַּ֣ד","s":"H5046","m":"Hc/VHw3ms","g":"and/ it was told"},{"w":"לְ/שָׁא֔וּל","s":"H7586","m":"HR/Npm","g":"to/ Saul"},{"w":"כִּי\\־","s":"H3588","m":"HTc","l":"כִּי","g":"that"},{"w":"בָ֥א","s":"H0935","m":"HVqp3ms","l":"בּוֹא","g":"he had gone"},{"w":"דָוִ֖ד","s":"H1732","m":"HNpm","l":"דָּוִד","g":"David"},{"w":"קְעִילָ֑ה","s":"H7084","m":"HNpl","l":"קְעִילָה","g":"Keilah"},{"w":"וַ/יֹּ֣אמֶר","s":"H0559","m":"Hc/Vqw3ms","g":"and/ he said"},{"w":"שָׁא֗וּל","s":"H7586","m":"HNpm","l":"שָׁאוּל","g":"Saul"},{"w":"נִכַּ֨ר","s":"H5234","m":"HVpp3ms","l":"נָכַר","g":"he has alienated"},{"w":"אֹת֤/וֹ","s":"H0853","m":"HTo/Sp3ms","l":"אֵת","g":"<obj.>/ him"},{"w":"אֱלֹהִים֙","s":"H0430","m":"HNcmpa","l":"אֱלֹהִים","g":"God"},{"w":"בְּ/יָדִ֔/י","s":"H3027","m":"HR/Ncbsc/Sp1bs","g":"in/ hand/ my"},{"w":"כִּ֚י","s":"H3588","m":"HTc","l":"כִּי","g":"for"},{"w":"נִסְגַּ֣ר","s":"H5462","m":"HVNp3ms","l":"סָגַר","g":"he has shut himself up"},{"w":"לָ/ב֔וֹא","s":"H0935","m":"HR/Vqcc","g":"by/ going"},{"w":"בְּ/עִ֖יר","s":"H5892","m":"HR/Ncfsc","g":"in/ a city of"},{"w":"דְּלָתַ֥יִם","s":"H1817","m":"HNcfda","l":"דֶּ֫לֶת","g":"doors"},{"w":"וּ/בְרִֽיחַ\\׃","s":"H1280","m":"HC/Ncmsa","g":"and/ bar[s]"}],"8":[{"w":"וַ/יְשַׁמַּ֥ע","s":"H8085","m":"Hc/Vpw3ms","g":"and/ he summoned"},{"w":"שָׁא֛וּל","s":"H7586","m":"HNpm","l":"שָׁאוּל","g":"Saul"},{"w":"אֶת\\־","s":"H0853","m":"HTo","l":"אֵת","g":"<obj.>"},{"w":"כָּל\\־","s":"H3605","m":"HNcmsc","l":"כֹּל","g":"all"},{"w":"הָ/עָ֖ם","s":"H5971","m":"HTd/Ncmsa","g":"the/ people"},{"w":"לַ/מִּלְחָמָ֑ה","s":"H4421","m":"HRd/Ncfsa","g":"for <the>/ battle"},{"w":"לָ/רֶ֣דֶת","s":"H3381","m":"HR/Vqcc","g":"to/ go down"},{"w":"קְעִילָ֔ה","s":"H7084","m":"HNpl","l":"קְעִילָה","g":"Keilah"},{"w":"לָ/צ֥וּר","s":"H6696","m":"HR/Vqcc","g":"to/ lay siege"},{"w":"אֶל\\־","s":"H0413","m":"HR","l":"אֶל","g":"against"},{"w":"דָּוִ֖ד","s":"H1732","m":"HNpm","l":"דָּוִד","g":"David"},{"w":"וְ/אֶל\\־","s":"H0413","m":"HC/R","g":"and/ against"},{"w":"אֲנָשָֽׁי/ו\\׃","s":"H0582","m":"HNcmpc/Sp3ms","l":"אֱנוֹשׁ","g":"men/ his"}],"9":[{"w":"וַ/יֵּ֣דַע","s":"H3045","m":"Hc/Vqw3ms","g":"and/ he knew"},{"w":"דָּוִ֔ד","s":"H1732","m":"HNpm","l":"דָּוִד","g":"David"},{"w":"כִּ֣י","s":"H3588","m":"HTc","l":"כִּי","g":"that"},{"w":"עָלָ֔י/ו","s":"H5921","m":"HRd/Sp3ms","l":"עַל","g":"on/ him"},{"w":"שָׁא֖וּל","s":"H7586","m":"HNpm","l":"שָׁאוּל","g":"Saul"},{"w":"מַחֲרִ֣ישׁ","s":"H2790","m":"HVhrmsa","l":"חָרַשׁ","g":"[was] plotting"},{"w":"הָ/רָעָ֑ה","s":"H7451","m":"HTd/Ncfsa","g":"<the>/ evil"},{"w":"וַ/יֹּ֙אמֶר֙","s":"H0559","m":"Hc/Vqw3ms","g":"and/ he said"},{"w":"אֶל\\־","s":"H0413","m":"HR","l":"אֶל","g":"to"},{"w":"אֶבְיָתָ֣ר","s":"H0054","m":"HNpm","l":"אֶבְיָתָר","g":"Abiathar"},{"w":"הַ/כֹּהֵ֔ן","s":"H3548","m":"HTd/Ncmsa","g":"the/ priest"},{"w":"הַגִּ֖ישָׁ/ה","s":"H5066","m":"HVhv2ms/Sh","l":"נָגַשׁ","g":"bring near/ !"},{"w":"הָ/אֵפֽוֹד\\׃\\ \\ס","s":"H0646","m":"HTd/Ncmsa","g":"the/ ephod"}],"10":[{"w":"וַ/יֹּאמֶר֮","s":"H0559","m":"Hc/Vqw3ms","g":"and/ he said"},{"w":"דָּוִד֒","s":"H1732","m":"HNpm","l":"דָּוִד","g":"David"},{"w":"יְהוָה֙","s":"H3068","m":"HNpt","l":"יהוה","g":"O Yahweh"},{"w":"אֱלֹהֵ֣י","s":"H0430","m":"HNcmpc","l":"אֱלֹהִים","g":"[the] God of"},{"w":"יִשְׂרָאֵ֔ל","s":"H3478","m":"HNpl","l":"יִשְׂרָאֵל","g":"Israel"},{"w":"שָׁמֹ֤עַ","s":"H8085","m":"HVqaa","l":"שָׁמַע","g":"certainly <to hear>"},{"w":"שָׁמַע֙","s":"H8085","m":"HVqp3ms","l":"שָׁמַע","g":"he has heard"},{"w":"עַבְדְּ/ךָ֔","s":"H5650","m":"HNcmsc/Sp2ms","l":"עֶ֫בֶד","g":"servant/ your"},{"w":"כִּֽי\\־","s":"H3588","m":"HTc","l":"כִּי","g":"that"},{"w":"מְבַקֵּ֥שׁ","s":"H1245","m":"HVprmsa","l":"בָּקַשׁ","g":"[is] seeking"},{"w":"שָׁא֖וּל","s":"H7586","m":"HNpm","l":"שָׁאוּל","g":"Saul"},{"w":"לָ/ב֣וֹא","s":"H0935","m":"HR/Vqcc","g":"to/ come"},{"w":"אֶל\\־","s":"H0413","m":"HR","l":"אֶל","g":"to"},{"w":"קְעִילָ֑ה","s":"H7084","m":"HNpl","l":"קְעִילָה","g":"Keilah"},{"w":"לְ/שַׁחֵ֥ת","s":"H7843","m":"HR/Vpcc","g":"to/ destroy"},{"w":"לָ/עִ֖יר","s":"H5892","m":"HRd/Ncfsa","g":"<to> the/ city"},{"w":"בַּ/עֲבוּרִֽ/י\\׃","s":"H5668","m":"HR/Ncmsc/Sp1bs","g":"because/ of/ me"}],"11":[{"w":"הֲ/יַסְגִּרֻ֣/נִי","s":"H5462","m":"HTi/Vhi3mp/Sp1bs","g":"¿/ will they deliver up/ me"},{"w":"בַעֲלֵי֩","s":"H1167","m":"HNcmpc","l":"בַּעַל","g":"[the] citizens of"},{"w":"קְעִילָ֨ה","s":"H7084","m":"HNpl","l":"קְעִילָה","g":"Keilah"},{"w":"בְ/יָד֜/וֹ","s":"H3027","m":"HR/Ncbsc/Sp3ms","g":"in/ hand/ his"},{"w":"הֲ/יֵרֵ֣ד","s":"H3381","m":"HTi/Vqi3ms","g":"¿/ will he come down"},{"w":"שָׁא֗וּל","s":"H7586","m":"HNpm","l":"שָׁאוּל","g":"Saul"},{"w":"כַּֽ/אֲשֶׁר֙","s":"H0834","m":"HR/Tr","g":"just/ as"},{"w":"שָׁמַ֣ע","s":"H8085","m":"HVqp3ms","l":"שָׁמַע","g":"he has heard"},{"w":"עַבְדֶּ֔/ךָ","s":"H5650","m":"HNcmsc/Sp2ms","l":"עֶ֫בֶד","g":"servant/ your"},{"w":"יְהוָה֙","s":"H3068","m":"HNpt","l":"יהוה","g":"O Yahweh"},{"w":"אֱלֹהֵ֣י","s":"H0430","m":"HNcmpc","l":"אֱלֹהִים","g":"[the] God of"},{"w":"יִשְׂרָאֵ֔ל","s":"H3478","m":"HNpl","l":"יִשְׂרָאֵל","g":"Israel"},{"w":"הַגֶּד\\־","s":"H5046","m":"HVhv2ms","l":"נָגַד","g":"tell"},{"w":"נָ֖א","s":"H4994","m":"HTj","l":"נָא","g":"please"},{"w":"לְ/עַבְדֶּ֑/ךָ\\ \\ס","s":"H5650","m":"HR/Ncmsc/Sp2ms","g":"to/ servant/ your"},{"w":"וַ/יֹּ֥אמֶר","s":"H0559","m":"Hc/Vqw3ms","g":"and/ he said"},{"w":"יְהוָ֖ה","s":"H3068","m":"HNpt","l":"יהוה","g":"Yahweh"},{"w":"יֵרֵֽד\\׃","s":"H3381","m":"HVqi3ms","l":"יָרַד","g":"he will come down"}],"12":[{"w":"וַ/יֹּ֣אמֶר","s":"H0559","m":"Hc/Vqw3ms","g":"and/ he said"},{"w":"דָּוִ֔ד","s":"H1732","m":"HNpm","l":"דָּוִד","g":"David"},{"w":"הֲ/יַסְגִּ֜רוּ","s":"H5462","m":"HTi/Vhi3mp","g":"¿/ will they deliver up"},{"w":"בַּעֲלֵ֧י","s":"H1167","m":"HNcmpc","l":"בַּעַל","g":"[the] citizens of"},{"w":"קְעִילָ֛ה","s":"H7084","m":"HNpl","l":"קְעִילָה","g":"Keilah"},{"w":"אֹתִ֥/י","s":"H0853","m":"HTo/Sp1bs","l":"אֵת","g":"<obj.>/ me"},{"w":"וְ/אֶת\\־","s":"H0853","m":"HC/To","g":"and/ <obj.>"},{"w":"אֲנָשַׁ֖/י","s":"H0582","m":"HNcmpc/Sp1bs","l":"אֱנוֹשׁ","g":"men/ my"},{"w":"בְּ/יַד\\־","s":"H3027","m":"HR/Ncbsc","g":"in/ [the] hand of"},{"w":"שָׁא֑וּל","s":"H7586","m":"HNpm","l":"שָׁאוּל","g":"Saul"},{"w":"וַ/יֹּ֥אמֶר","s":"H0559","m":"Hc/Vqw3ms","g":"and/ he said"},{"w":"יְהוָ֖ה","s":"H3068","m":"HNpt","l":"יהוה","g":"Yahweh"},{"w":"יַסְגִּֽירוּ\\׃\\ \\ס","s":"H5462","m":"HVhi3mp","l":"סָגַר","g":"they will deliver [you] up"}],"13":[{"w":"וַ/יָּקָם֩","s":"H6965","m":"Hc/Vqw3ms","g":"and/ he arose"},{"w":"דָּוִ֨ד","s":"H1732","m":"HNpm","l":"דָּוִד","g":"David"},{"w":"וַ/אֲנָשָׁ֜י/ו","s":"H0582","m":"HC/Ncmpc/Sp3ms","g":"and/ men/ his"},{"w":"כְּ/שֵׁשׁ\\־","s":"H8337","m":"HR/Ncbsa","g":"about/ six"},{"w":"מֵא֣וֹת","s":"H3967","m":"HNcfpa","l":"מֵאָה","g":"hundred<s>"},{"w":"אִ֗ישׁ","s":"H0376","m":"HNcmsa","l":"אִישׁ","g":"man"},{"w":"וַ/יֵּצְאוּ֙","s":"H3318","m":"Hc/Vqw3mp","g":"and/ they went out"},{"w":"מִ/קְּעִלָ֔ה","s":"H7084","m":"HR/Npl","g":"from/ Keilah"},{"w":"וַ/יִּֽתְהַלְּכ֖וּ","s":"H1980","m":"Hc/Vtw3mp","g":"and/ they went about"},{"w":"בַּ/אֲשֶׁ֣ר","s":"H0834","m":"HR/Tr","g":"at/ where"},{"w":"יִתְהַלָּ֑כוּ","s":"H1980","m":"HVti3mp","l":"הָלַךְ","g":"they went about"},{"w":"וּ/לְ/שָׁא֣וּל","s":"H7586","m":"HC/R/Npm","g":"and/ to/ Saul"},{"w":"הֻגַּ֗ד","s":"H5046","m":"HVHp3ms","l":"נָגַד","g":"it was told"},{"w":"כִּֽי\\־","s":"H3588","m":"HTc","l":"כִּי","g":"that"},{"w":"נִמְלַ֤ט","s":"H4422","m":"HVNp3ms","l":"מָלַט","g":"he had escaped"},{"w":"דָּוִד֙","s":"H1732","m":"HNpm","l":"דָּוִד","g":"David"},{"w":"מִ/קְּעִילָ֔ה","s":"H7084","m":"HR/Npl","g":"from/ Keilah"},{"w":"וַ/יֶּחְדַּ֖ל","s":"H2308","m":"Hc/Vqw3ms","g":"and/ he ceased"},{"w":"לָ/צֵֽאת\\׃","s":"H3318","m":"HR/Vqcc","g":"to/ go forth"}],"14":[{"w":"וַ/יֵּ֨שֶׁב","s":"H3427","m":"Hc/Vqw3ms","g":"and/ he dwelt"},{"w":"דָּוִ֤ד","s":"H1732","m":"HNpm","l":"דָּוִד","g":"David"},{"w":"בַּ/מִּדְבָּר֙","s":"H4057","m":"HRd/Ncmsa","g":"in the/ wilderness"},{"w":"בַּ/מְּצָד֔וֹת","s":"H4679","m":"HRd/Ncfpa","g":"in the/ strongholds"},{"w":"וַ/יֵּ֥שֶׁב","s":"H3427","m":"Hc/Vqw3ms","g":"and/ he dwelt"},{"w":"בָּ/הָ֖ר","s":"H2022","m":"HRd/Ncmsa","g":"in the/ hill country"},{"w":"בְּ/מִדְבַּר\\־","s":"H4057","m":"HR/Ncmsc","g":"in/ [the] wilderness of"},{"w":"זִ֑יף","s":"H2128","m":"HNpl","l":"זִיף","g":"Ziph"},{"w":"וַ/יְבַקְשֵׁ֤/הוּ","s":"H1245","m":"Hc/Vpw3ms/Sp3ms","g":"and/ he sought/ him"},{"w":"שָׁאוּל֙","s":"H7586","m":"HNpm","l":"שָׁאוּל","g":"Saul"},{"w":"כָּל\\־","s":"H3605","m":"HNcmsc","l":"כֹּל","g":"all"},{"w":"הַ/יָּמִ֔ים","s":"H3117","m":"HTd/Ncmpa","g":"the/ days"},{"w":"וְ/לֹֽא\\־","s":"H3808","m":"HC/Tn","g":"and/ not"},{"w":"נְתָנ֥/וֹ","s":"H5414","m":"HVqp3ms/Sp3ms","l":"נָתַן","g":"he gave/ him"},{"w":"אֱלֹהִ֖ים","s":"H0430","m":"HNcmpa","l":"אֱלֹהִים","g":"God"},{"w":"בְּ/יָדֽ/וֹ\\׃","s":"H3027","m":"HR/Ncbsc/Sp3ms","g":"in/ hand/ his"}],"15":[{"w":"וַ/יַּ֣רְא","s":"H7200","m":"Hc/Vqw3ms","g":"and/ he saw"},{"w":"דָוִ֔ד","s":"H1732","m":"HNpm","l":"דָּוִד","g":"David"},{"w":"כִּֽי\\־","s":"H3588","m":"HTc","l":"כִּי","g":"that"},{"w":"יָצָ֥א","s":"H3318","m":"HVqp3ms","l":"יָצָא","g":"he had come forth"},{"w":"שָׁא֖וּל","s":"H7586","m":"HNpm","l":"שָׁאוּל","g":"Saul"},{"w":"לְ/בַקֵּ֣שׁ","s":"H1245","m":"HR/Vpcc","g":"to/ seek"},{"w":"אֶת\\־","s":"H0853","m":"HTo","l":"אֵת","g":"<obj.>"},{"w":"נַפְשׁ֑/וֹ","s":"H5315","m":"HNcfsc/Sp3ms","l":"נֶ֫פֶשׁ","g":"life/ his"},{"w":"וְ/דָוִ֥ד","s":"H1732","m":"HC/Npm","g":"and/ David"},{"w":"בְּ/מִדְבַּר\\־","s":"H4057","m":"HR/Ncmsc","g":"[was] in/ [the] wilderness of"},{"w":"זִ֖יף","s":"H2128","m":"HNpl","l":"זִיף","g":"Ziph"},{"w":"בַּ/חֹֽרְשָׁה\\׃\\ \\ס","s":"H2793","m":"HRd/Npl","g":"at <the>/ Horesh"}],"16":[{"w":"וַ/יָּ֙קָם֙","s":"H6965","m":"Hc/Vqw3ms","g":"and/ he arose"},{"w":"יְהוֹנָתָ֣ן","s":"H3083","m":"HNpm","l":"יְהוֹנָתָן","g":"Jonathan"},{"w":"בֶּן\\־","s":"H1121","m":"HNcmsc","l":"בֵּן","g":"[the] son of"},{"w":"שָׁא֔וּל","s":"H7586","m":"HNpm","l":"שָׁאוּל","g":"Saul"},{"w":"וַ/יֵּ֥לֶךְ","s":"H1980","m":"Hc/Vqw3ms","g":"and/ he went"},{"w":"אֶל\\־","s":"H0413","m":"HR","l":"אֶל","g":"to"},{"w":"דָּוִ֖ד","s":"H1732","m":"HNpm","l":"דָּוִד","g":"David"},{"w":"חֹ֑רְשָׁה","s":"H2793","m":"HNpl","l":"חֹ֫רֶשׁ","g":"Horesh"},{"w":"וַ/יְחַזֵּ֥ק","s":"H2388","m":"Hc/Vpw3ms","g":"and/ he strengthened"},{"w":"אֶת\\־","s":"H0853","m":"HTo","l":"אֵת","g":"<obj.>"},{"w":"יָד֖/וֹ","s":"H3027","m":"HNcbsc/Sp3ms","l":"יָד","g":"hand/ his"},{"w":"בֵּ/אלֹהִֽים\\׃","s":"H0430","m":"HR/Ncmpa","g":"in/ God"}],"17":[{"w":"וַ/יֹּ֨אמֶר","s":"H0559","m":"Hc/Vqw3ms","g":"and/ he said"},{"w":"אֵלָ֜י/ו","s":"H0413","m":"HRd/Sp3ms","l":"אֶל","g":"to/ him"},{"w":"אַל\\־","s":"H0408","m":"HTn","l":"אַל","g":"may not"},{"w":"תִּירָ֗א","s":"H3372","m":"HVqj2ms","l":"יָרֵא","g":"you be afraid"},{"w":"כִּ֠י","s":"H3588","m":"HTc","l":"כִּי","g":"for"},{"w":"לֹ֤א","s":"H3808","m":"HTn","l":"לֹא","g":"not"},{"w":"תִֽמְצָאֲ/ךָ֙","s":"H4672","m":"HVqi3fs/Sp2ms","l":"מָצָא","g":"it will find/ you"},{"w":"יַ֚ד","s":"H3027","m":"HNcbsc","l":"יָד","g":"[the] hand of"},{"w":"שָׁא֣וּל","s":"H7586","m":"HNpm","l":"שָׁאוּל","g":"Saul"},{"w":"אָבִ֔/י","s":"H0001","m":"HNcmsc/Sp1bs","l":"אָב","g":"father/ my"},{"w":"וְ/אַתָּה֙","s":"H0859","m":"HC/Pp2ms","g":"and/ you"},{"w":"תִּמְלֹ֣ךְ","s":"H4427","m":"HVqi2ms","l":"מָלַךְ","g":"you will reign"},{"w":"עַל\\־","s":"H5921","m":"HR","l":"עַל","g":"over"},{"w":"יִשְׂרָאֵ֔ל","s":"H3478","m":"HNpl","l":"יִשְׂרָאֵל","g":"Israel"},{"w":"וְ/אָנֹכִ֖י","s":"H0595","m":"HC/Pp1bs","g":"and/ I"},{"w":"אֶֽהְיֶה\\־","s":"H1961","m":"HVqi1cs","l":"הָיָה","g":"I will become"},{"w":"לְּ/ךָ֣","s":"H9031","m":"HRd/Sp2ms","g":"to <the>/ you"},{"w":"לְ/מִשְׁנֶ֑ה","s":"H4932","m":"HR/Ncmsa","g":"<into>/ second in rank"},{"w":"וְ/גַם\\־","s":"H1571","m":"HC/D","g":"and/ also"},{"w":"שָׁא֥וּל","s":"H7586","m":"HNpm","l":"שָׁאוּל","g":"Saul"},{"w":"אָבִ֖/י","s":"H0001","m":"HNcmsc/Sp1bs","l":"אָב","g":"father/ my"},{"w":"יֹדֵ֥עַ","s":"H3045","m":"HVqrmsa","l":"יָדַע","g":"[is] knowing"},{"w":"כֵּֽן\\׃","s":"H3651","m":"HD","l":"כֵּן","g":"[it is] thus"}],"18":[{"w":"וַ/יִּכְרְת֧וּ","s":"H3772","m":"Hc/Vqw3mp","g":"and/ they made"},{"w":"שְׁנֵי/הֶ֛ם","s":"H8147","m":"HNcbdc/Sp3mp","l":"שְׁנַ֫יִם","g":"[the] two of/ them"},{"w":"בְּרִ֖ית","s":"H1285","m":"HNcfsa","l":"בְּרִית","g":"a covenant"},{"w":"לִ/פְנֵ֣י","s":"H6440","m":"HR/Ncmpc","g":"<to>/ before"},{"w":"יְהוָ֑ה","s":"H3068","m":"HNpt","l":"יהוה","g":"Yahweh"},{"w":"וַ/יֵּ֤שֶׁב","s":"H3427","m":"Hc/Vqw3ms","g":"and/ he remained"},{"w":"דָּוִד֙","s":"H1732","m":"HNpm","l":"דָּוִד","g":"David"},{"w":"בַּ/חֹ֔רְשָׁה","s":"H2793","m":"HRd/Npl","g":"at <the>/ Horesh"},{"w":"וִ/יהוֹנָתָ֖ן","s":"H3083","m":"HC/Npm","g":"and/ Jonathan"},{"w":"הָלַ֥ךְ","s":"H1980","m":"HVqp3ms","l":"הָלַךְ","g":"he went"},{"w":"לְ/בֵיתֽ/וֹ\\׃\\ \\ס","s":"H1004","m":"HR/Ncmsc/Sp3ms","g":"to/ house/ his"}],"19":[{"w":"וַ/יַּעֲל֤וּ","s":"H5927","m":"Hc/Vqw3mp","g":"and/ they went up"},{"w":"זִפִים֙","s":"H2130","m":"HNgmpa","l":"זִיפִי","g":"Ziphites"},{"w":"אֶל\\־","s":"H0413","m":"HR","l":"אֶל","g":"to"},{"w":"שָׁא֔וּל","s":"H7586","m":"HNpm","l":"שָׁאוּל","g":"Saul"},{"w":"הַ/גִּבְעָ֖תָ/ה","s":"H1390","m":"HTd/Npl/Sd","g":"<the>/ Gibeah/ towards"},{"w":"לֵ/אמֹ֑ר","s":"H0559","m":"HR/Vqcc","g":"<to>/ saying"},{"w":"הֲ/ל֣וֹא","s":"H3808","m":"HTi/Tn","g":"¿/ not"},{"w":"דָ֠וִד","s":"H1732","m":"HNpm","l":"דָּוִד","g":"[is] David"},{"w":"מִסְתַּתֵּ֨ר","s":"H5641","m":"HVtrmsa","l":"סָתַר","g":"hiding himself"},{"w":"עִמָּ֤/נוּ","s":"H5973","m":"HRd/Sp1bp","l":"עִם","g":"with/ us"},{"w":"בַ/מְּצָדוֹת֙","s":"H4679","m":"HRd/Ncfpa","g":"in the/ strongholds"},{"w":"בַּ/חֹ֔רְשָׁה","s":"H2793","m":"HRd/Npl","g":"at <the>/ Horesh"},{"w":"בְּ/גִבְעַת֙","s":"H1389","m":"HR/Ncfsc","g":"on/ [the] hill of"},{"w":"הַֽ/חֲכִילָ֔ה","s":"H2444","m":"HTd/Npl","g":"<the>/ Hakilah"},{"w":"אֲשֶׁ֖ר","s":"H0834","m":"HTr","l":"אֲשֶׁר","g":"which"},{"w":"מִ/ימִ֥ין","s":"H3225","m":"HR/Ncfsc","g":"[is] from/ [the] south of"},{"w":"הַ/יְשִׁימֽוֹן\\׃","s":"H3452","m":"HTd/Npl","g":"<the>/ Jeshimon"}],"20":[{"w":"וְ֠/עַתָּה","s":"H6258","m":"HC/D","g":"and/ now"},{"w":"לְ/כָל\\־","s":"H3605","m":"HR/Ncmsc","g":"to/ all"},{"w":"אַוַּ֨ת","s":"H0185","m":"HNcfsc","l":"אַוָּה","g":"[the] desire of"},{"w":"נַפְשְׁ/ךָ֥","s":"H5315","m":"HNcfsc/Sp2ms","l":"נֶ֫פֶשׁ","g":"self/ your"},{"w":"הַ/מֶּ֛לֶךְ","s":"H4428","m":"HTd/Ncmsa","g":"O/ king"},{"w":"לָ/רֶ֖דֶת","s":"H3381","m":"HR/Vqcc","g":"to/ come down"},{"w":"רֵ֑ד","s":"H3381","m":"HVqv2ms","l":"יָרַד","g":"come down"},{"w":"וְ/לָ֥/נוּ","s":"H9035","m":"HC/Rd/Sp1bp","g":"and/ [belongs] to <the>/ us"},{"w":"הַסְגִּיר֖/וֹ","s":"H5462","m":"HVhcc/Sp3ms","l":"סָגַר","g":"to deliver up/ him"},{"w":"בְּ/יַ֥ד","s":"H3027","m":"HR/Ncbsc","g":"in/ [the] hand of"},{"w":"הַ/מֶּֽלֶךְ\\׃","s":"H4428","m":"HTd/Ncmsa","g":"the/ king"}],"21":[{"w":"וַ/יֹּ֣אמֶר","s":"H0559","m":"Hc/Vqw3ms","g":"and/ he said"},{"w":"שָׁא֔וּל","s":"H7586","m":"HNpm","l":"שָׁאוּל","g":"Saul"},{"w":"בְּרוּכִ֥ים","s":"H1288","m":"HVqsmpa","l":"בָּרַךְ","g":"[be] blessed"},{"w":"אַתֶּ֖ם","s":"H0859","m":"HPp2mp","l":"אַתֶּם","g":"you"},{"w":"לַֽ/יהוָ֑ה","s":"H3068","m":"HR/Npt","g":"by/ Yahweh"},{"w":"כִּ֥י","s":"H3588","m":"HTc","l":"כִּי","g":"for"},{"w":"חֲמַלְתֶּ֖ם","s":"H2550","m":"HVqp2mp","l":"חָמַל","g":"you have had compassion"},{"w":"עָלָֽ/י\\׃","s":"H5921","m":"HRd/Sp1bs","l":"עַל","g":"on/ me"}],"22":[{"w":"לְכוּ\\־","s":"H1980","m":"HVqv2mp","l":"הָלַךְ","g":"go"},{"w":"נָ֞א","s":"H4994","m":"HTj","l":"נָא","g":"please"},{"w":"הָכִ֣ינוּ","s":"H3559","m":"HVhv2mp","l":"כּוּן","g":"prepare"},{"w":"ע֗וֹד","s":"H5750","m":"HAcmsa","l":"עוֹד","g":"still"},{"w":"וּ/דְע֤וּ","s":"H3045","m":"HC/Vqv2mp","g":"and/ know"},{"w":"וּ/רְאוּ֙","s":"H7200","m":"HC/Vqv2mp","g":"and/ see"},{"w":"אֶת\\־","s":"H0853","m":"HTo","l":"אֵת","g":"<obj.>"},{"w":"מְקוֹמ/וֹ֙","s":"H4725","m":"HNcmsc/Sp3ms","l":"מָקוֹם","g":"place/ his"},{"w":"אֲשֶׁ֣ר","s":"H0834","m":"HTr","l":"אֲשֶׁר","g":"where"},{"w":"תִּֽהְיֶ֣ה","s":"H1961","m":"HVqi3fs","l":"הָיָה","g":"it is"},{"w":"רַגְל֔/וֹ","s":"H7272","m":"HNcfsc/Sp3ms","l":"רֶ֫גֶל","g":"foot/ his"},{"w":"מִ֥י","s":"H4310","m":"HPi","l":"מִי","g":"who?"},{"w":"רָאָ֖/הוּ","s":"H7200","m":"HVqp3ms/Sp3ms","l":"רָאָה","g":"has he seen/ him"},{"w":"שָׁ֑ם","s":"H8033","m":"HD","l":"שָׁם","g":"there"},{"w":"כִּ֚י","s":"H3588","m":"HTc","l":"כִּי","g":"for"},{"w":"אָמַ֣ר","s":"H0559","m":"HVqp3ms","l":"אָמַר","g":"someone has said"},{"w":"אֵלַ֔/י","s":"H0413","m":"HRd/Sp1bs","l":"אֶל","g":"to/ me"},{"w":"עָר֥וֹם","s":"H6191","m":"HVqaa","l":"עָרֹם","g":"certainly <to be crafty>"},{"w":"יַעְרִ֖ם","s":"H6191","m":"HVqi3ms","l":"עָרֹם","g":"he is crafty"},{"w":"הֽוּא\\׃","s":"H1931","m":"HPp3ms","l":"הוּא","g":"he"}],"23":[{"w":"וּ/רְא֣וּ","s":"H7200","m":"HC/Vqv2mp","g":"and/ see"},{"w":"וּ/דְע֗וּ","s":"H3045","m":"HC/Vqv2mp","g":"and/ know"},{"w":"מִ/כֹּ֤ל","s":"H3605","m":"HR/Ncmsc","g":"from/ all"},{"w":"הַ/מַּֽחֲבֹאִים֙","s":"H4224","m":"HTd/Ncmpa","g":"the/ hiding places"},{"w":"אֲשֶׁ֣ר","s":"H0834","m":"HTr","l":"אֲשֶׁר","g":"where"},{"w":"יִתְחַבֵּ֣א","s":"H2244","m":"HVti3ms","l":"חָבָא","g":"he hides himself"},{"w":"שָׁ֔ם","s":"H8033","m":"HD","l":"שָׁם","g":"there"},{"w":"וְ/שַׁבְתֶּ֤ם","s":"H7725","m":"Hc/Vqq2mp","g":"and/ you will return"},{"w":"אֵלַ/י֙","s":"H0413","m":"HRd/Sp1bs","l":"אֶל","g":"to/ me"},{"w":"אֶל\\־","s":"H0413","m":"HR","l":"אֶל","g":"to"},{"w":"נָכ֔וֹן","s":"H3559","m":"HVNrmsa","l":"כּוּן","g":"a certain [thing]"},{"w":"וְ/הָלַכְתִּ֖י","s":"H1980","m":"Hc/Vqq1cs","g":"and/ I will go"},{"w":"אִתְּ/כֶ֑ם","s":"H0854","m":"HRd/Sp2mp","l":"אֵת","g":"with/ you"},{"w":"וְ/הָיָה֙","s":"H1961","m":"Hc/Vqq3ms","g":"and/ it will be"},{"w":"אִם\\־","s":"H0518","m":"HTc","l":"אִם","g":"if"},{"w":"יֶשְׁנ֣/וֹ","s":"H3426","m":"HAcbsc/Sp3ms","l":"יֵשׁ","g":"there/ he"},{"w":"בָ/אָ֔רֶץ","s":"H0776","m":"HRd/Ncfsa","g":"[is] in the/ land"},{"w":"וְ/חִפַּשְׂתִּ֣י","s":"H2664","m":"Hc/Vpq1cs","g":"and/ I will search out"},{"w":"אֹת֔/וֹ","s":"H0853","m":"HTo/Sp3ms","l":"אֵת","g":"<obj.>/ him"},{"w":"בְּ/כֹ֖ל","s":"H3605","m":"HR/Ncmsc","g":"among/ all"},{"w":"אַלְפֵ֥י","s":"H0505","m":"HNcbpc","l":"אֶ֫לֶף","g":"[the] thousands of"},{"w":"יְהוּדָֽה\\׃","s":"H3063","m":"HNpl","l":"יְהוּדָה","g":"Judah"}],"24":[{"w":"וַ/יָּק֛וּמוּ","s":"H6965","m":"Hc/Vqw3mp","g":"and/ they arose"},{"w":"וַ/יֵּלְכ֥וּ","s":"H1980","m":"Hc/Vqw3mp","g":"and/ they went"},{"w":"זִ֖יפָ/ה","s":"H2128","m":"HNpl/Sd","l":"זִיף","g":"Ziph/ towards"},{"w":"לִ/פְנֵ֣י","s":"H6440","m":"HR/Ncmpc","g":"<to>/ before"},{"w":"שָׁא֑וּל","s":"H7586","m":"HNpm","l":"שָׁאוּל","g":"Saul"},{"w":"וְ/דָוִ֨ד","s":"H1732","m":"HC/Npm","g":"and/ David"},{"w":"וַ/אֲנָשָׁ֜י/ו","s":"H0582","m":"HC/Ncmpc/Sp3ms","g":"and/ men/ his"},{"w":"בְּ/מִדְבַּ֤ר","s":"H4057","m":"HR/Ncmsc","g":"[were] in/ [the] wilderness of"},{"w":"מָעוֹן֙","s":"H4584","m":"HNpl","l":"מָעוֹן","g":"Maon"},{"w":"בָּ/עֲרָבָ֔ה","s":"H6160","m":"HRd/Npl","g":"in the/ Arabah"},{"w":"אֶ֖ל","s":"H0413","m":"HR","l":"אֶל","g":"to"},{"w":"יְמִ֥ין","s":"H3225","m":"HNcfsc","l":"יָמִין","g":"[the] south of"},{"w":"הַ/יְשִׁימֽוֹן\\׃","s":"H3452","m":"HTd/Npl","g":"<the>/ Jeshimon"}],"25":[{"w":"וַ/יֵּ֨לֶךְ","s":"H1980","m":"Hc/Vqw3ms","g":"and/ he went"},{"w":"שָׁא֣וּל","s":"H7586","m":"HNpm","l":"שָׁאוּל","g":"Saul"},{"w":"וַ/אֲנָשָׁי/ו֮","s":"H0582","m":"HC/Ncmpc/Sp3ms","g":"and/ men/ his"},{"w":"לְ/בַקֵּשׁ֒","s":"H1245","m":"HR/Vpcc","g":"to/ seek [him]"},{"w":"וַ/יַּגִּ֣דוּ","s":"H5046","m":"Hc/Vhw3mp","g":"and/ people told"},{"w":"לְ/דָוִ֔ד","s":"H1732","m":"HR/Npm","g":"to/ David"},{"w":"וַ/יֵּ֣רֶד","s":"H3381","m":"Hc/Vqw3ms","g":"and/ he went down"},{"w":"הַ/סֶּ֔לַע","s":"H5553","m":"HTd/Ncmsa","g":"the/ rock"},{"w":"וַ/יֵּ֖שֶׁב","s":"H3427","m":"Hc/Vqw3ms","g":"and/ he remained"},{"w":"בְּ/מִדְבַּ֣ר","s":"H4057","m":"HR/Ncmsc","g":"in/ [the] wilderness of"},{"w":"מָע֑וֹן","s":"H4584","m":"HNpl","l":"מָעוֹן","g":"Maon"},{"w":"וַ/יִּשְׁמַ֣ע","s":"H8085","m":"Hc/Vqw3ms","g":"and/ he heard"},{"w":"שָׁא֔וּל","s":"H7586","m":"HNpm","l":"שָׁאוּל","g":"Saul"},{"w":"וַ/יִּרְדֹּ֥ף","s":"H7291","m":"Hc/Vqw3ms","g":"and/ he pursued"},{"w":"אַחֲרֵֽי\\־","s":"H0310","m":"HAcmpc","l":"אַחַר","g":"after"},{"w":"דָוִ֖ד","s":"H1732","m":"HNpm","l":"דָּוִד","g":"David"},{"w":"מִדְבַּ֥ר","s":"H4057","m":"HNcmsc","l":"מִדְבָּר","g":"[the] wilderness of"},{"w":"מָעֽוֹן\\׃","s":"H4584","m":"HNpl","l":"מָעוֹן","g":"Maon"}],"26":[{"w":"וַ/יֵּ֨לֶךְ","s":"H1980","m":"Hc/Vqw3ms","g":"and/ he went"},{"w":"שָׁא֜וּל","s":"H7586","m":"HNpm","l":"שָׁאוּל","g":"Saul"},{"w":"מִ/צַּ֤ד","s":"H6654","m":"HR/Ncmsc","g":"from/ [the] side of"},{"w":"הָ/הָר֙","s":"H2022","m":"HTd/Ncmsa","g":"the/ mountain"},{"w":"מִ/זֶּ֔ה","s":"H2088","m":"HR/Tm","g":"from/ this"},{"w":"וְ/דָוִ֧ד","s":"H1732","m":"HC/Npm","g":"and/ David"},{"w":"וַ/אֲנָשָׁ֛י/ו","s":"H0582","m":"HC/Ncmpc/Sp3ms","g":"and/ men/ his"},{"w":"מִ/צַּ֥ד","s":"H6654","m":"HR/Ncmsc","g":"[were] from/ [the] side of"},{"w":"הָ/הָ֖ר","s":"H2022","m":"HTd/Ncmsa","g":"the/ mountain"},{"w":"מִ/זֶּ֑ה","s":"H2088","m":"HR/Tm","g":"from/ this"},{"w":"וַ/יְהִ֨י","s":"H1961","m":"Hc/Vqw3ms","g":"and/ he was"},{"w":"דָוִ֜ד","s":"H1732","m":"HNpm","l":"דָּוִד","g":"David"},{"w":"נֶחְפָּ֤ז","s":"H2648","m":"HVNrmsa","l":"חָפַז","g":"hurrying away"},{"w":"לָ/לֶ֙כֶת֙","s":"H1980","m":"HR/Vqcc","g":"to/ go"},{"w":"מִ/פְּנֵ֣י","s":"H6440","m":"HR/Ncmpc","g":"from/ before"},{"w":"שָׁא֔וּל","s":"H7586","m":"HNpm","l":"שָׁאוּל","g":"Saul"},{"w":"וְ/שָׁא֣וּל","s":"H7586","m":"HC/Npm","g":"and/ Saul"},{"w":"וַ/אֲנָשָׁ֗י/ו","s":"H0582","m":"HC/Ncmpc/Sp3ms","g":"and/ men/ his"},{"w":"עֹֽטְרִ֛ים","s":"H5849","m":"HVqrmpa","l":"עָטַר","g":"[were] surrounding"},{"w":"אֶל\\־","s":"H0413","m":"HR","l":"אֶל","g":"<to>"},{"w":"דָּוִ֥ד","s":"H1732","m":"HNpm","l":"דָּוִד","g":"David"},{"w":"וְ/אֶל\\־","s":"H0413","m":"HC/R","g":"and/ <to>"},{"w":"אֲנָשָׁ֖י/ו","s":"H0582","m":"HNcmpc/Sp3ms","l":"אֱנוֹשׁ","g":"men/ his"},{"w":"לְ/תָפְשָֽׂ/ם\\׃","s":"H8610","m":"HR/Vqcc/Sp3mp","g":"to/ catch/ them"}],"27":[{"w":"וּ/מַלְאָ֣ךְ","s":"H4397","m":"HC/Ncmsa","g":"and/ a messenger"},{"w":"בָּ֔א","s":"H0935","m":"HVqp3ms","l":"בּוֹא","g":"he came"},{"w":"אֶל\\־","s":"H0413","m":"HR","l":"אֶל","g":"to"},{"w":"שָׁא֖וּל","s":"H7586","m":"HNpm","l":"שָׁאוּל","g":"Saul"},{"w":"לֵ/אמֹ֑ר","s":"H0559","m":"HR/Vqcc","g":"<to>/ saying"},{"w":"מַהֲרָ֣/ה","s":"H4116","m":"HVpv2ms/Sh","l":"מָהַר","g":"make haste/ !"},{"w":"וְ/לֵ֔כָ/ה","s":"H1980","m":"HC/Vqv2ms/Sh","g":"and/ come/ !"},{"w":"כִּֽי\\־","s":"H3588","m":"HTc","l":"כִּי","g":"for"},{"w":"פָשְׁט֥וּ","s":"H6584","m":"HVqp3cp","l":"פָּשַׁט","g":"they have made a raid"},{"w":"פְלִשְׁתִּ֖ים","s":"H6430","m":"HNgmpa","l":"פְּלִשְׁתִּי","g":"[the] Philistines"},{"w":"עַל\\־","s":"H5921","m":"HR","l":"עַל","g":"on"},{"w":"הָ/אָֽרֶץ\\׃","s":"H0776","m":"HTd/Ncfsa","g":"the/ land"}],"28":[{"w":"וַ/יָּ֣שָׁב","s":"H7725","m":"Hc/Vqw3ms","g":"and/ he turned back"},{"w":"שָׁא֗וּל","s":"H7586","m":"HNpm","l":"שָׁאוּל","g":"Saul"},{"w":"מִ/רְדֹף֙","s":"H7291","m":"HR/Vqcc","g":"from/ pursuing"},{"w":"אַחֲרֵ֣י","s":"H0310","m":"HAcmpc","l":"אַחַר","g":"after"},{"w":"דָוִ֔ד","s":"H1732","m":"HNpm","l":"דָּוִד","g":"David"},{"w":"וַ/יֵּ֖לֶךְ","s":"H1980","m":"Hc/Vqw3ms","g":"and/ he went"},{"w":"לִ/קְרַ֣את","s":"H7122","m":"HR/Vqcc","g":"to/ meet"},{"w":"פְּלִשְׁתִּ֑ים","s":"H6430","m":"HNgmpa","l":"פְּלִשְׁתִּי","g":"[the] Philistines"},{"w":"עַל\\־","s":"H5921","m":"HR","l":"עַל","g":"there-"},{"w":"כֵּ֗ן","s":"H3651","m":"HD","l":"כֵּן","g":"-fore"},{"w":"קָֽרְאוּ֙","s":"H7121","m":"HVqp3cp","l":"קָרָא","g":"people called"},{"w":"לַ/מָּק֣וֹם","s":"H4725","m":"HRd/Ncmsa","g":"<to> the/ place"},{"w":"הַ/ה֔וּא","s":"H1931","m":"HTd/Pp3ms","g":"<the>/ that"},{"w":"סֶ֖לַע","s":"H5555","m":"HNcmsc","l":"סֶלַע הַמַּחְלְקוֹת","g":"Sela"},{"w":"הַֽמַּחְלְקֽוֹת\\׃","s":"H5555","m":"HNpl","l":"סֶלַע הַמַּחְלְקוֹת","g":"Hammahlekoth"}]}